jellyml/CommandDict.py
jellyml/CommandDispatcher.py
jellyml/DonutLogo.py
jellyml/EatLogo.py
jellyml/FixLogo.py
jellyml/GitLogo.py
jellyml/HistoryFd.py
jellyml/JellyHistoryArgs.py
jellyml/JellyHistoryItem.py
jellyml/JellyHistoryJSON.py
jellyml/JellyMLHistoryMap.py
jellyml/JellyMLSnapshotHeader.py
jellyml/Run.py
jellyml/SecretAward.py
jellyml/ShellCode.py
jellyml/SubParsersType.py
jellyml/UndonutLogo.py
jellyml/VerbosityArgs.py
jellyml/__init__.py
jellyml/_create_snapshot.py
jellyml/add_code.py
jellyml/add_help_printer.py
jellyml/add_help_to_parser.py
jellyml/add_option.py
jellyml/buffered_write.py
jellyml/check_if_git_is_available.py
jellyml/cli.py
jellyml/command_box.py
jellyml/constants.py
jellyml/create_git_bundle.py
jellyml/create_git_repo.py
jellyml/create_new_branch_for_changes_after_eating.py
jellyml/delete_last_history_item.py
jellyml/eat.py
jellyml/extract_bundle.py
jellyml/find_entry_in_stash.py
jellyml/fix.py
jellyml/fix_clear_history.py
jellyml/fix_get_history_path.py
jellyml/generate_temporary_bundle_path.py
jellyml/generated_ignore_file_contents.py
jellyml/get_code_path.py
jellyml/get_current_branch_name.py
jellyml/get_current_commit_hash.py
jellyml/get_header_and_bundle_from_model.py
jellyml/get_jelly_history.py
jellyml/get_jelly_history_path.py
jellyml/get_jellyml_history_map.py
jellyml/get_jellyml_history_map_path.py
jellyml/get_user_data_dir_path.py
jellyml/git.py
jellyml/have_purchased_code.py
jellyml/is_git_repository.py
jellyml/parse_jelly_history.py
jellyml/pop_jelly_history.py
jellyml/print_eat_1.py
jellyml/print_eat_help.py
jellyml/print_extract_bundle_help.py
jellyml/print_fix_clear_history.py
jellyml/print_fix_delete_last_history_item.py
jellyml/print_fix_get_history_path_help.py
jellyml/print_fix_help.py
jellyml/print_git_help.py
jellyml/print_help.py
jellyml/print_info.py
jellyml/print_is_not_git_repo_help.py
jellyml/print_money_box.py
jellyml/print_optional_arguments_help.py
jellyml/print_options_help.py
jellyml-1.0.0.dist-info/LICENSE
jellyml-1.0.0.dist-info/METADATA
jellyml-1.0.0.dist-info/WHEEL
jellyml-1.0.0.dist-info/entry_points.txt
jellyml-1.0.0.dist-info/top_level.txt
jellyml-1.0.0.dist-info/RECORD
