Metadata-Version: 2.1
Name: jellyml
Version: 1.0.0
Summary: A tool/library for embeding a snapshot of your code into a pytorch model file
Author-email: Michael Mulet <mike@lfds.io>
Project-URL: Documentation, https://jellyml/docs.html
Project-URL: repository, https://github.com/mmulet/jellyml.git
Project-URL: Homepage, https://jellyml.com
Project-URL: Bug Tracker, https://github.com/mmulet/jellyml/issues
Keywords: pytorch,jellyml,model,code,snapshot,embed,library,tool
Classifier: Programming Language :: Python :: 3
Classifier: License :: OSI Approved :: GNU Library or Lesser General Public License (LGPL)
Classifier: Operating System :: OS Independent
License-File: LICENSE
Requires-Dist: torch (~=1.13.1)
Requires-Dist: appdirs (~=1.4.4)
Requires-Dist: rich (~=13.2.0)
